cpTool/__init__.py
cpTool/__main__.py
cpTool/api.py
cpTool/git.py
cpTool/customModules/__init__.py
cpTool/customModules/htmlGenerator.py
cpTool/customModules/readmeFIleGenerator.py
cp_tool-2.1.2.dist-info/LICENSE
cp_tool-2.1.2.dist-info/METADATA
cp_tool-2.1.2.dist-info/WHEEL
cp_tool-2.1.2.dist-info/entry_points.txt
cp_tool-2.1.2.dist-info/top_level.txt
cp_tool-2.1.2.dist-info/RECORD
