Metadata-Version: 2.1
Name: cp-tool
Version: 2.1.2
Summary: cp-tool is an auto generator tool for solved problems at different online judges
Home-page: https://github.com/jspw/cp-tool
Author: jspw
Author-email: mhshifat757@gmail.com
License: MIT License
Classifier: Programming Language :: Python :: 3
Classifier: License :: OSI Approved :: MIT License
Classifier: Operating System :: OS Independent
Requires-Python: >=3.6
License-File: LICENSE
Requires-Dist: requests
